kenzy_image/VERSION
kenzy_image/__init__.py
kenzy_image/__main__.py
kenzy_image/core.py
kenzy_image/resources/mobilenet_v3/frozen_inference_graph.pb
kenzy_image/resources/mobilenet_v3/labels.txt
kenzy_image/resources/mobilenet_v3/ssd_mobilenet_v3_large_coco_2020_01_14.pbtxt
kenzy_image/resources/yolov7/config.json
kenzy_image/resources/yolov7/labels.txt
kenzy_image/resources/yolov7/yolov7-tiny.pt
kenzy_image-1.0.0.dist-info/LICENSE
kenzy_image-1.0.0.dist-info/METADATA
kenzy_image-1.0.0.dist-info/WHEEL
kenzy_image-1.0.0.dist-info/top_level.txt
kenzy_image-1.0.0.dist-info/zip-safe
kenzy_image-1.0.0.dist-info/RECORD
