Metadata-Version: 2.1
Name: kenzy-image
Version: 1.0.0
Summary: Computer Vision module for Python 3.x+ to perform face/object/motion detection and recognition.
Home-page: https://kenzy.ai
Author: lnxusr1
Author-email: dist@kenzy.ai
License: MIT
Download-URL: https://kenzy.ai/get/kenzy-image/latest
Project-URL: Bug Tracker, https://kenzy.ai/issues/kenzy-image
Project-URL: Changelog, https://kenzy.ai/get/kenzy-image/latest/changelog
Keywords: OpenCV,Face Detection,Object Detection,Face Recognition,Motion Detection
Platform: UNKNOWN
Classifier: License :: OSI Approved :: MIT License
Classifier: Programming Language :: Python :: 3
Classifier: Operating System :: OS Independent
Requires-Python: >=3.6
License-File: LICENSE
Requires-Dist: face-recognition
Requires-Dist: numpy
Requires-Dist: opencv-contrib-python
Requires-Dist: yolov7detect
